llm_perplexity.py
llm_perplexity-2025.12.0.dist-info/licenses/LICENSE
llm_perplexity-2025.12.0.dist-info/METADATA
llm_perplexity-2025.12.0.dist-info/WHEEL
llm_perplexity-2025.12.0.dist-info/entry_points.txt
llm_perplexity-2025.12.0.dist-info/top_level.txt
llm_perplexity-2025.12.0.dist-info/RECORD
