Metadata-Version: 2.4
Name: llm-perplexity
Version: 2025.12.0
Summary: LLM access to pplx-api 3 by Perplexity Labs
Author: hex
License: Apache-2.0
Project-URL: Homepage, https://github.com/hex/llm-perplexity
Project-URL: Changelog, https://github.com/hex/llm-perplexity/releases
Requires-Python: >=3.7
License-File: LICENSE
Requires-Dist: llm
Requires-Dist: openai>=1.0.0
Provides-Extra: test
Requires-Dist: pytest>=7.0.0; extra == "test"
Requires-Dist: python-dotenv>=1.0.0; extra == "test"
Requires-Dist: pillow>=9.0.0; extra == "test"
Dynamic: license-file
